{
  "indexes": [
    {
      "collectionGroup": "games",
      "queryScope": "COLLECTION",
      "fields": [
        {
          "fieldPath": "creator_id",
          "order": "ASCENDING"
        },
        {
          "fieldPath": "scheduled_time",
          "order": "ASCENDING"
        },
        {
          "fieldPath": "__name__",
          "order": "ASCENDING"
        }
      ],
      "density": "SPARSE_ALL"
    },
    {
      "collectionGroup": "games",
      "queryScope": "COLLECTION",
      "fields": [
        {
          "fieldPath": "participant_ids",
          "arrayConfig": "CONTAINS"
        },
        {
          "fieldPath": "scheduled_time",
          "order": "ASCENDING"
        },
        {
          "fieldPath": "__name__",
          "order": "ASCENDING"
        }
      ],
      "density": "SPARSE_ALL"
    }
  ],
  "fieldOverrides": []
}
